camunda_connector/__init__.py
camunda_connector/connector.py
camunda_connector/models.py
camunda_connector/py.typed
camunda_connector_python-0.2.0.dist-info/licenses/LICENSE
camunda_connector_python-0.2.0.dist-info/METADATA
camunda_connector_python-0.2.0.dist-info/WHEEL
camunda_connector_python-0.2.0.dist-info/top_level.txt
camunda_connector_python-0.2.0.dist-info/RECORD
