Metadata-Version: 2.4
Name: camunda-connector-python
Version: 0.2.0
Summary: A micro library for building Camunda connectors in Python using decorators
Author-email: Pavel Kotelevskii <pavel.kotelevskii@camunda.com>
Maintainer-email: Pavel Kotelevskii <pavel.kotelevskii@camunda.com>
License: MIT License
Project-URL: Homepage, https://github.com/chillleader/camunda-connector-py
Project-URL: Documentation, https://github.com/chillleader/camunda-connector-py#readme
Project-URL: Repository, https://github.com/chillleader/camunda-connector-py
Project-URL: Bug Tracker, https://github.com/chillleader/camunda-connector-py/issues
Keywords: camunda,connector,bpmn,workflow,automation
Classifier: Development Status :: 4 - Beta
Classifier: Intended Audience :: Developers
Classifier: Operating System :: OS Independent
Classifier: Programming Language :: Python :: 3
Classifier: Programming Language :: Python :: 3.9
Classifier: Programming Language :: Python :: 3.10
Classifier: Programming Language :: Python :: 3.11
Classifier: Programming Language :: Python :: 3.12
Classifier: Topic :: Software Development :: Libraries :: Python Modules
Classifier: Topic :: Office/Business :: Office Suites
Classifier: Topic :: System :: Distributed Computing
Requires-Python: >=3.8
License-File: LICENSE
Requires-Dist: fastapi>=0.100.0
Requires-Dist: pydantic>=2.0.0
Requires-Dist: httpx>=0.24.0
Requires-Dist: uvicorn[standard]>=0.20.0
Provides-Extra: dev
Requires-Dist: pytest>=7.0.0; extra == "dev"
Requires-Dist: pytest-asyncio>=0.21.0; extra == "dev"
Requires-Dist: pytest-cov>=4.0.0; extra == "dev"
Requires-Dist: black>=23.0.0; extra == "dev"
Requires-Dist: isort>=5.12.0; extra == "dev"
Requires-Dist: mypy>=1.0.0; extra == "dev"
Requires-Dist: pre-commit>=3.0.0; extra == "dev"
Requires-Dist: build>=0.10.0; extra == "dev"
Requires-Dist: twine>=4.0.0; extra == "dev"
Requires-Dist: types-requests>=2.31.0; extra == "dev"
Dynamic: license-file
